foo/__init__.py
foodemo2-0.0.2.dist-info/LICENSE
foodemo2-0.0.2.dist-info/METADATA
foodemo2-0.0.2.dist-info/WHEEL
foodemo2-0.0.2.dist-info/top_level.txt
foodemo2-0.0.2.dist-info/RECORD
